ocflzw_decompress/__init__.py
ocflzw_decompress/lzw.py
tests/__init__.py
tests/test_decompress.py
ocflzw_decompress-1.0.0.dist-info/LICENSE
ocflzw_decompress-1.0.0.dist-info/METADATA
ocflzw_decompress-1.0.0.dist-info/WHEEL
ocflzw_decompress-1.0.0.dist-info/top_level.txt
ocflzw_decompress-1.0.0.dist-info/RECORD
