Metadata-Version: 2.1
Name: ocflzw-decompress
Version: 1.0.0
Summary: OCFLZW Decompress
Home-page: https://github.com/plessbd/ocflzw-decompress
Author: Ben Plessinger, Mohammad Zia
License: GNU General Public License v3 (GPLv3)
Project-URL: Bug Tracker, https://github.com/plessbd/ocflzw-decompress/issues
Keywords: lzw ocfblob decompress cerner
Platform: UNKNOWN
Classifier: Programming Language :: Python :: 3
Requires-Python: >=3.6
License-File: LICENSE
